common/__init__.py
common/config.py
common/constants.py
common/dyna_global.py
common/systems.py
db/__init__.py
db/db_manager.py
hdb_explorer/__init__.py
hdb_explorer/__main__.py
hdb_explorer/common/__init__.py
hdb_explorer/common/config.py
hdb_explorer/common/constants.py
hdb_explorer/common/dyna_global.py
hdb_explorer/common/systems.py
hdb_explorer/db/__init__.py
hdb_explorer/db/db_manager.py
hdb_explorer/ui/__init__.py
hdb_explorer/ui/add_system.py
hdb_explorer/ui/app.py
hdb_explorer/ui/db_tree.py
hdb_explorer/ui/edit_system.py
hdb_explorer/ui/header.py
hdb_explorer/ui/main.py
hdb_explorer/ui/sql_editor.py
hdb_explorer/ui/sql_result_viewer.py
ui/__init__.py
ui/add_system.py
ui/app.py
ui/db_tree.py
ui/edit_system.py
ui/header.py
ui/main.py
ui/sql_editor.py
ui/sql_result_viewer.py
hdb_explorer-0.0.3.dist-info/LICENSE
hdb_explorer-0.0.3.dist-info/METADATA
hdb_explorer-0.0.3.dist-info/WHEEL
hdb_explorer-0.0.3.dist-info/entry_points.txt
hdb_explorer-0.0.3.dist-info/top_level.txt
hdb_explorer-0.0.3.dist-info/RECORD
