Metadata-Version: 2.1
Name: hdb-explorer
Version: 0.0.3
Summary: A simple SAP HANA Database Explorer.
Author: Praveen Nair
Author-email: 
License: MIT
Project-URL: Source Repository, https://github.com/praveen-nair/hdb_explorer/
Project-URL: Issues, https://github.com/praveen-nair/hdb_explorer/issues
License-File: LICENSE
Requires-Dist: hdbcli (>=2.24.24)
Requires-Dist: httpx (>=0.27.2)
Requires-Dist: textual (>=5.3.0)
Requires-Dist: textual-autocomplete (>=4.0.5)
Requires-Dist: textual[syntax]
Requires-Dist: typing-extensions (>=4.12.2)
